django_runprod/__init__.py
django_runprod/gunicorn.py
django_runprod/py.typed
django_runprod/management/__init__.py
django_runprod/management/commands/__init__.py
django_runprod/management/commands/runprod.py
django_runprod-0.1.2.dist-info/METADATA
django_runprod-0.1.2.dist-info/WHEEL
django_runprod-0.1.2.dist-info/RECORD
